[
    {
        "id": 1,
        "title": "Chair",
        "description": "The Darcy bedside locker has been designed.",
        "image": "./images/chair1.webp",
        "price": "$365"
    },
    {
        "id": 2,
        "title": "Chair",
        "description": "The Darcy bedside locker has been designed.",
        "image": "./images/chair2.webp",
        "price": "$365"
    },
    {
        "id": 3,
        "title": "Chair",
        "description": "The Darcy bedside locker has been designed.",
        "image": "./images/chair3.webp",
        "price": "$365"
    },
    {
        "id": 4,
        "title": "Chair",
        "description": "The Darcy bedside locker has been designed.",
        "image": "./images/chair4.jpg",
        "price": "$365"
    },
    {
        "id": 5,
        "title": "Chair",
        "description": "The Darcy bedside locker has been designed.",
        "image": "./images/chair5.jpg",
        "price": "$365"
    },
    {
        "id": 6,
        "title": "Chair",
        "description": "The Darcy bedside locker has been designed.",
        "image": "./images/chair6.jpg",
        "price": "$365"
    }

]